bidsonym/__init__.py
bidsonym/_version.py
bidsonym/defacing_algorithms.py
bidsonym/reports.py
bidsonym/run_deeid.py
bidsonym/utils.py
bidsonym/tests/__init__.py
bidsonym/tests/test_example.py
bidsonym-0.0.4.dist-info/AUTHORS.rst
bidsonym-0.0.4.dist-info/LICENSE
bidsonym-0.0.4.dist-info/METADATA
bidsonym-0.0.4.dist-info/WHEEL
bidsonym-0.0.4.dist-info/entry_points.txt
bidsonym-0.0.4.dist-info/top_level.txt
bidsonym-0.0.4.dist-info/RECORD
