Metadata-Version: 2.1
Name: bidsonym
Version: 0.0.4
Summary: A BIDSapp for deidentification of neuroimaging data.
Home-page: https://github.com/peerherholz/bidsonym
Author: Peer Herholz
Author-email: herholz.peer@gmail.com
License: BSD (3-clause)
Platform: UNKNOWN
Classifier: Development Status :: 2 - Pre-Alpha
Classifier: Natural Language :: English
Classifier: Programming Language :: Python :: 3
Requires-Python: >=3.6
Requires-Dist: argparse
Requires-Dist: pandas
Requires-Dist: nibabel
Requires-Dist: nipype
Requires-Dist: nilearn
Requires-Dist: duecredit
Requires-Dist: pybids
